instadown/__init__.py
instadown/ig.py
instadown-0.1.7.dist-info/LICENSE
instadown-0.1.7.dist-info/METADATA
instadown-0.1.7.dist-info/WHEEL
instadown-0.1.7.dist-info/entry_points.txt
instadown-0.1.7.dist-info/top_level.txt
instadown-0.1.7.dist-info/RECORD
