Metadata-Version: 2.1
Name: instadown
Version: 0.1.7
Summary: Download all the public posts of a public Instagram account
Home-page: https://github.com/IamStefin/Instagram-Image-Downloader
Author: Stef
Author-email: sstefin@bk.ru
License: MIT
Platform: UNKNOWN
Classifier: License :: OSI Approved :: MIT License
Classifier: Programming Language :: Python
Classifier: Programming Language :: Python :: 3
Classifier: Programming Language :: Python :: 3.6
Classifier: Programming Language :: Python :: Implementation :: CPython
Classifier: Programming Language :: Python :: Implementation :: PyPy
Requires-Python: >=3.6.0
Requires-Dist: requests
Requires-Dist: wget
